<?xml version="1.0" encoding="UTF-8"?>
<con:soapui-project id="1b056a1c-03b6-403d-9ff2-ca137f77bfd0" created="3.53.0" activeEnvironment="Default environment" encryptionMode="Not encrypted" name="REST Project 2" projectVersion="" updated="3.53.0 2024-05-13T12:06:25Z" xmlns:con="http://eviware.com/soapui/config">
  <con:settings/>
  <con:interface xsi:type="con:RestService" id="39b59a54-0c9c-4d5d-bac3-9e2660a8a99f" wadlVersion="http://wadl.dev.java.net/2009/02" name="http://POST operation] https:" type="rest" xmlns:xsi="http://www.w3.org/2001/XMLSchema-instance">
    <con:settings id="65d82930-42a5-4c36-8fea-3a95e4a46a8b"/>
    <con:definitionCache type="TEXT" rootPart=""/>
    <con:endpoints>
      <con:endpoint>https://petstore.swagger.io</con:endpoint>
    </con:endpoints>
    <con:resource name="User" path="v2/user" id="b699359b-49dc-4bff-8e2e-1cc335461c51">
      <con:settings/>
      <con:parameters/>
      <con:method name="User" id="c80fda4d-30ab-479c-9bd4-9acd0cff26c4" method="POST">
        <con:settings/>
        <con:parameters/>
        <con:representation type="FAULT">
          <con:mediaType>application/xml</con:mediaType>
          <con:status>404</con:status>
          <con:params/>
          <con:element>apiResponse</con:element>
        </con:representation>
        <con:representation type="REQUEST">
          <con:mediaType>application/json</con:mediaType>
          <con:params/>
        </con:representation>
        <con:representation type="RESPONSE">
          <con:mediaType>application/json</con:mediaType>
          <con:status>200</con:status>
          <con:params/>
          <con:element xmlns:user="https://petstore.swagger.io/v2/user/petstore.swagger.io/v2/user">user:Response</con:element>
        </con:representation>
        <con:request name="Request 1" id="c80bb012-e504-4c68-8a53-66f460b37490" mediaType="application/json" postQueryString="false">
          <con:settings/>
          <con:endpoint>https://petstore.swagger.io</con:endpoint>
          <con:request/>
          <con:credentials>
            <con:selectedAuthProfile>No Authorization</con:selectedAuthProfile>
            <con:authType>No Authorization</con:authType>
          </con:credentials>
          <con:jmsConfig JMSDeliveryMode="PERSISTENT"/>
          <con:parameters/>
        </con:request>
      </con:method>
    </con:resource>
  </con:interface>
  <con:interface xsi:type="con:RestService" id="26089d1f-66eb-4577-96d1-e2fe25e90333" wadlVersion="http://wadl.dev.java.net/2009/02" name="https://petstore.swagger.io" type="rest" xmlns:xsi="http://www.w3.org/2001/XMLSchema-instance">
    <con:settings id="4d78d54e-aef6-409f-bd27-eb0cd1da0980"/>
    <con:definitionCache type="TEXT" rootPart=""/>
    <con:endpoints>
      <con:endpoint>https://petstore.swagger.io</con:endpoint>
    </con:endpoints>
    <con:resource name="Login" path="/v2/user/login" id="9513bf03-5f96-4724-80ec-648c246b1cc0">
      <con:settings/>
      <con:parameters/>
      <con:method name="Login" id="b7cd47b2-1679-4ff2-b9af-09edc82619a5" method="GET">
        <con:settings/>
        <con:parameters>
          <con:parameter required="true">
            <con:name>username</con:name>
            <con:value>{username}</con:value>
            <con:style>QUERY</con:style>
            <con:default>{username}</con:default>
            <con:path xsi:nil="true"/>
            <con:description xsi:nil="true"/>
          </con:parameter>
          <con:parameter required="true">
            <con:name>password</con:name>
            <con:value>{password}</con:value>
            <con:style>QUERY</con:style>
            <con:default>{password}</con:default>
            <con:path xsi:nil="true"/>
            <con:description xsi:nil="true"/>
          </con:parameter>
        </con:parameters>
        <con:representation type="RESPONSE">
          <con:mediaType>application/json</con:mediaType>
          <con:status>200</con:status>
          <con:params/>
          <con:element xmlns:log="https://petstore.swagger.io/v2/user/login">log:Response</con:element>
        </con:representation>
        <con:request name="Request 1" id="bbe6a528-1b08-4ad7-8caf-9e897fd214d3" mediaType="application/json">
          <con:settings/>
          <con:endpoint>https://petstore.swagger.io</con:endpoint>
          <con:request/>
          <con:credentials>
            <con:selectedAuthProfile>No Authorization</con:selectedAuthProfile>
            <con:authType>No Authorization</con:authType>
          </con:credentials>
          <con:jmsConfig JMSDeliveryMode="PERSISTENT"/>
          <con:parameters>
            <con:entry key="password" value="{password}"/>
            <con:entry key="username" value="{username}"/>
          </con:parameters>
          <con:parameterOrder>
            <con:entry>username</con:entry>
            <con:entry>password</con:entry>
          </con:parameterOrder>
        </con:request>
      </con:method>
    </con:resource>
    <con:resource name="Username" path="/v2/user/{username}" id="d35b96bd-fc87-43ab-aec8-ed29af759fee">
      <con:settings/>
      <con:parameters/>
      <con:method name="Username" id="80887073-5027-4ee5-851f-f7952bdde5ee" method="GET">
        <con:settings/>
        <con:parameters>
          <con:parameter required="true">
            <con:name>username</con:name>
            <con:value>username</con:value>
            <con:style>TEMPLATE</con:style>
            <con:default>username</con:default>
            <con:path xsi:nil="true"/>
            <con:description xsi:nil="true"/>
          </con:parameter>
        </con:parameters>
        <con:representation type="FAULT">
          <con:mediaType>application/json</con:mediaType>
          <con:status>404</con:status>
          <con:params/>
          <con:element xmlns:user="https://petstore.swagger.io/v2/user/username">user:Fault</con:element>
        </con:representation>
        <con:representation type="FAULT">
          <con:mediaType>application/xml</con:mediaType>
          <con:status>405</con:status>
          <con:params/>
          <con:element>apiResponse</con:element>
        </con:representation>
        <con:representation type="RESPONSE">
          <con:mediaType>application/json</con:mediaType>
          <con:status>200</con:status>
          <con:params/>
          <con:element xmlns:user="https://petstore.swagger.io/v2/user/username">user:Response</con:element>
        </con:representation>
        <con:request name="Request 1" id="f6ca18e5-6d62-4014-992e-a86f822c2d60" mediaType="application/json">
          <con:settings/>
          <con:endpoint>https://petstore.swagger.io</con:endpoint>
          <con:parameters>
            <con:entry key="username" value="username"/>
          </con:parameters>
          <con:parameterOrder>
            <con:entry>username</con:entry>
          </con:parameterOrder>
        </con:request>
      </con:method>
      <con:method name="Username 2" id="36692000-2413-4df6-87d2-5fa1b86c06d7" method="DELETE">
        <con:settings/>
        <con:parameters>
          <con:parameter required="true">
            <con:name>username</con:name>
            <con:value>username</con:value>
            <con:style>TEMPLATE</con:style>
            <con:default>username</con:default>
            <con:path xsi:nil="true"/>
            <con:description xsi:nil="true"/>
          </con:parameter>
        </con:parameters>
        <con:representation type="REQUEST">
          <con:mediaType>application/json</con:mediaType>
          <con:params/>
        </con:representation>
        <con:representation type="FAULT">
          <con:mediaType xsi:nil="true"/>
          <con:status>404</con:status>
          <con:params/>
          <con:element>data</con:element>
        </con:representation>
        <con:representation type="RESPONSE">
          <con:mediaType>application/json</con:mediaType>
          <con:status>200</con:status>
          <con:params/>
          <con:element xmlns:joh="https://petstore.swagger.io/v2/user/JohnDoe">joh:Response</con:element>
        </con:representation>
        <con:request name="Request 1" id="325147e3-1134-4a5e-a046-3d536aeedd58" mediaType="application/json">
          <con:settings/>
          <con:endpoint>https://petstore.swagger.io</con:endpoint>
          <con:parameters>
            <con:entry key="username" value="username"/>
          </con:parameters>
          <con:parameterOrder>
            <con:entry>username</con:entry>
          </con:parameterOrder>
        </con:request>
      </con:method>
    </con:resource>
    <con:resource name="Logout" path="/v2/user/logout" id="43ed0940-da6c-4ed1-9058-b37acab3c9d3">
      <con:settings/>
      <con:parameters/>
      <con:method name="Logout" id="b7a07573-bce0-4028-b067-00d0f5563b6b" method="GET">
        <con:settings/>
        <con:parameters/>
        <con:representation type="RESPONSE">
          <con:mediaType>application/json</con:mediaType>
          <con:status>200</con:status>
          <con:params/>
          <con:element xmlns:log="https://petstore.swagger.io/v2/user/logout">log:Response</con:element>
        </con:representation>
        <con:request name="Request 1" id="cd40b916-819f-4783-896c-7f05100b90b4" mediaType="application/json">
          <con:settings/>
          <con:endpoint>https://petstore.swagger.io</con:endpoint>
          <con:parameters/>
        </con:request>
      </con:method>
    </con:resource>
  </con:interface>
  <con:testSuite id="7a1fef03-b50b-4a82-a192-9aa96efa8e7b" name="http://POST operation] https: Test Suite">
    <con:settings id="b25d4ce1-e59e-4f4b-b273-849ec2ea75e7"/>
    <con:runType>SEQUENTIAL</con:runType>
    <con:testCase id="7b054016-07b1-4b13-893d-fd925544ebdd" discardOkResults="false" failOnError="false" failTestCaseOnErrors="true" keepSession="false" name="Test Case" searchProperties="true" timeout="0">
      <con:settings/>
      <con:testStep type="restrequest" name="Request 1" id="49b05710-b3d8-4756-80cd-59a14404eb99">
        <con:settings/>
        <con:config service="http://POST operation] https:" resourcePath="/v2/user" methodName="User" xsi:type="con:RestRequestStep" xmlns:xsi="http://www.w3.org/2001/XMLSchema-instance">
          <con:restRequest name="Request 1" id="c80bb012-e504-4c68-8a53-66f460b37490" mediaType="application/json" postQueryString="false">
            <con:settings>
              <con:setting id="com.eviware.soapui.impl.wsdl.WsdlRequest@request-headers">&lt;xml-fragment/></con:setting>
            </con:settings>
            <con:endpoint>https://petstore.swagger.io</con:endpoint>
            <con:request>{
    "id": 2,
    "username": "testuser1",
    "firstName": "John",
    "lastName": "Doe",
    "email": "john@doe.com",
    "password": "testuser",
    "phone": "234567890",
    "userStatus": 0
}</con:request>
            <con:originalUri>https://petstore.swagger.io/v2/user/petstore.swagger.io/v2/user</con:originalUri>
            <con:assertion type="Valid HTTP Status Codes" id="36fde155-accb-46b8-9257-594768c17aec" name="Valid HTTP Status Codes">
              <con:settings/>
              <con:configuration>
                <codes>200</codes>
              </con:configuration>
            </con:assertion>
            <con:credentials>
              <con:selectedAuthProfile>No Authorization</con:selectedAuthProfile>
              <con:authType>No Authorization</con:authType>
            </con:credentials>
            <con:jmsConfig JMSDeliveryMode="PERSISTENT"/>
            <con:parameters/>
          </con:restRequest>
        </con:config>
      </con:testStep>
      <con:testStep type="restrequest" name="Request 2" id="9a21cee3-fbd1-4bf5-b9af-cd5c8fe2bc1b">
        <con:settings/>
        <con:config service="https://petstore.swagger.io" resourcePath="/v2/user/login" methodName="Login" xsi:type="con:RestRequestStep" xmlns:xsi="http://www.w3.org/2001/XMLSchema-instance">
          <con:restRequest name="Request 2" id="bbe6a528-1b08-4ad7-8caf-9e897fd214d3" mediaType="application/json">
            <con:settings>
              <con:setting id="com.eviware.soapui.impl.wsdl.WsdlRequest@request-headers">&lt;xml-fragment/></con:setting>
            </con:settings>
            <con:endpoint>https://petstore.swagger.io</con:endpoint>
            <con:request/>
            <con:originalUri>https://petstore.swagger.io/v2/user/login</con:originalUri>
            <con:assertion type="Valid HTTP Status Codes" id="b044e7bd-7a19-43b3-948e-ceab508b2f2d" name="Valid HTTP Status Codes">
              <con:settings/>
              <con:configuration>
                <codes>200</codes>
              </con:configuration>
            </con:assertion>
            <con:credentials>
              <con:selectedAuthProfile>No Authorization</con:selectedAuthProfile>
              <con:authType>No Authorization</con:authType>
            </con:credentials>
            <con:jmsConfig JMSDeliveryMode="PERSISTENT"/>
            <con:parameters>
              <con:entry key="password" value="JohnsPassword"/>
              <con:entry key="username" value="JohnDoe"/>
            </con:parameters>
            <con:parameterOrder>
              <con:entry>username</con:entry>
              <con:entry>password</con:entry>
            </con:parameterOrder>
          </con:restRequest>
        </con:config>
      </con:testStep>
      <con:testStep type="restrequest" name="Request 3" id="4a75c3c8-1d7d-4785-8f87-35811c0f4895">
        <con:settings/>
        <con:config service="https://petstore.swagger.io" resourcePath="/v2/user/{username}" methodName="Username" xsi:type="con:RestRequestStep" xmlns:xsi="http://www.w3.org/2001/XMLSchema-instance">
          <con:restRequest name="Request 3" id="f6ca18e5-6d62-4014-992e-a86f822c2d60" mediaType="application/json">
            <con:settings>
              <con:setting id="com.eviware.soapui.impl.wsdl.WsdlRequest@request-headers">&lt;xml-fragment/></con:setting>
            </con:settings>
            <con:endpoint>https://petstore.swagger.io</con:endpoint>
            <con:request/>
            <con:originalUri>https://petstore.swagger.io/v2/user/username</con:originalUri>
            <con:assertion type="Valid HTTP Status Codes" id="860f263b-4563-423c-8292-560ab1f4caf4" name="Valid HTTP Status Codes">
              <con:settings/>
              <con:configuration>
                <codes>200</codes>
              </con:configuration>
            </con:assertion>
            <con:credentials>
              <con:selectedAuthProfile>No Authorization</con:selectedAuthProfile>
              <con:authType>No Authorization</con:authType>
            </con:credentials>
            <con:jmsConfig JMSDeliveryMode="PERSISTENT"/>
            <con:parameters>
              <con:entry key="username" value="testuser1"/>
            </con:parameters>
            <con:parameterOrder>
              <con:entry>username</con:entry>
            </con:parameterOrder>
          </con:restRequest>
        </con:config>
      </con:testStep>
      <con:testStep type="restrequest" name="Request 4" id="c8fbce34-3857-41c9-80f6-ee373765d2c7">
        <con:settings/>
        <con:config service="https://petstore.swagger.io" resourcePath="/v2/user/logout" methodName="Logout" xsi:type="con:RestRequestStep" xmlns:xsi="http://www.w3.org/2001/XMLSchema-instance">
          <con:restRequest name="Request 4" id="cd40b916-819f-4783-896c-7f05100b90b4" mediaType="application/json">
            <con:settings>
              <con:setting id="com.eviware.soapui.impl.wsdl.WsdlRequest@request-headers">&lt;xml-fragment/></con:setting>
            </con:settings>
            <con:endpoint>https://petstore.swagger.io</con:endpoint>
            <con:request/>
            <con:originalUri>https://petstore.swagger.io/v2/user/logout</con:originalUri>
            <con:assertion type="Valid HTTP Status Codes" id="69048dd7-7998-48d3-bdba-c556546521bc" name="Valid HTTP Status Codes">
              <con:settings/>
              <con:configuration>
                <codes>200</codes>
              </con:configuration>
            </con:assertion>
            <con:credentials>
              <con:selectedAuthProfile>No Authorization</con:selectedAuthProfile>
              <con:authType>No Authorization</con:authType>
            </con:credentials>
            <con:jmsConfig JMSDeliveryMode="PERSISTENT"/>
            <con:parameters/>
          </con:restRequest>
        </con:config>
      </con:testStep>
      <con:testStep type="restrequest" name="Request 5" id="c5195137-7192-46b6-bc9c-436e982b9c55">
        <con:settings/>
        <con:config service="https://petstore.swagger.io" resourcePath="/v2/user/{username}" methodName="Username 2" xsi:type="con:RestRequestStep" xmlns:xsi="http://www.w3.org/2001/XMLSchema-instance">
          <con:restRequest name="Request 5" id="325147e3-1134-4a5e-a046-3d536aeedd58" mediaType="application/json" postQueryString="false">
            <con:settings>
              <con:setting id="com.eviware.soapui.impl.wsdl.WsdlRequest@request-headers">&lt;xml-fragment/></con:setting>
            </con:settings>
            <con:endpoint>https://petstore.swagger.io</con:endpoint>
            <con:request/>
            <con:originalUri>https://petstore.swagger.io/v2/user/JohnDoe</con:originalUri>
            <con:assertion type="Valid HTTP Status Codes" id="346e4848-da11-46ca-92c2-daa12c6ba52d" name="Valid HTTP Status Codes">
              <con:settings/>
              <con:configuration>
                <codes>200</codes>
              </con:configuration>
            </con:assertion>
            <con:credentials>
              <con:selectedAuthProfile>No Authorization</con:selectedAuthProfile>
              <con:authType>No Authorization</con:authType>
            </con:credentials>
            <con:jmsConfig JMSDeliveryMode="PERSISTENT"/>
            <con:parameters>
              <con:entry key="username" value="testuser1"/>
            </con:parameters>
            <con:parameterOrder>
              <con:entry>username</con:entry>
            </con:parameterOrder>
          </con:restRequest>
        </con:config>
      </con:testStep>
      <con:properties/>
      <con:reportParameters/>
    </con:testCase>
    <con:properties/>
    <con:reportParameters/>
  </con:testSuite>
  <con:properties/>
  <con:wssContainer/>
  <con:databaseConnectionContainer/>
  <con:jmsConnectionContainer/>
  <con:oAuth2ProfileContainer/>
  <con:oAuth1ProfileContainer/>
  <con:reporting>
    <con:xmlTemplates/>
    <con:parameters/>
  </con:reporting>
  <con:eventHandlers type="RequestFilter.filterRequest" name="RequestFilter.filterRequest">
    <con:script>// Sample event script to add custom HTTP header to all outgoing REST, SOAP and HTTP(S) calls
// This code is often used for adding custom authentication to ReadyAPI functional tests

// If hardcoding the token, uncomment and change line 5
// token = '4567'

// If your token is parameterized in Project level custom property, uncomment line 8
// token = request.parent.testCase.testSuite.project.getProperty('auth_token').getValue()

// To modify all outgoing calls, remove comments from lines 11 to 16
// headers = request.requestHeaders
// if (headers.containsKey('auth_token2') == false) {
//   headers.put('auth_token2', token)
//   request.requestHeaders = headers
// }</con:script>
  </con:eventHandlers>
  <con:eventHandlers type="TestRunListener.afterStep" name="TestRunListener.afterStep">
    <con:script>// Save all test step results into files
// Change the directory path in line 5 to a location where you want to store details
// then uncomment lines 5 to 10

// filePath = 'C:\\tempOutputDirectory\\'
// fos = new java.io.FileOutputStream(filePath + testStepResult.testStep.label + '.txt', true)
// pw = new java.io.PrintWriter(fos)
// testStepResult.writeTo(pw)
// pw.close()
// fos.close()</con:script>
  </con:eventHandlers>
  <con:authRepository/>
  <con:tags/>
</con:soapui-project>
